<soapenv:Envelope xmlns:soapenc="http://schemas.xmlsoap.org/soap/encoding/" xmlns:soapenv="http://schemas.xmlsoap.org/soap/envelope/" xmlns:xsd="http://www.w3.org/2001/XMLSchema" xmlns:xsi="http://www.w3.org/2001/XMLSchema-instance"><soapenv:Body><NS1:ObjectNGOut xmlns:NS1="http://issk.ugd.mos.ru/MSG_RC/ObjectNGOut/v1.0"><NS1:requestID>a41c340e-08e0-11e5-89b9-ac1050040000</NS1:requestID><NS1:delete>0</NS1:delete><NS1:Object><pref:Object xmlns:pref="http://xmlns.oracle.com/MSG_RC_ObjectNG"><pref:ObjectID>0F76A1F8EA32B4E1C325746D003ECBE4</pref:ObjectID><pref:ObjectName>Гараж-стоянка открытого типа</pref:ObjectName><pref:ObjectArea>СВАО</pref:ObjectArea><pref:ObjectDistrict>Северный</pref:ObjectDistrict><pref:ObjectAddress>Москва, СВАО, район Северный, МКАД 82 км, корп. 1</pref:ObjectAddress><pref:PointXY><pref:Contour><ns1:description xmlns:ns1="http://www.opengis.net/gml">0F76A1F8EA32B4E1C325746D003ECBE4</ns1:description><pref:OgrFID>128079766</pref:OgrFID><pref:GEOMETRY xmlns:NS1="http://www.w3.org/1999/xlink" NS1:type="simple"><ns1:Point xmlns:ns1="http://www.opengis.net/gml" srsName="EPSG:4326"><ns1:coordinates cs="," decimal="." ts=" ">37.5481670404449,55.9096967714196 </ns1:coordinates></ns1:Point></pref:GEOMETRY></pref:Contour></pref:PointXY><pref:ConstructionWorkType>Новое строительство</pref:ConstructionWorkType><pref:MainFunctional>Гаражи и автостоянки</pref:MainFunctional><pref:SourceOfFinance>Внебюджетные источники</pref:SourceOfFinance><pref:Square/><pref:Floor>5</pref:Floor><pref:ObjectStatus>В строительстве</pref:ObjectStatus><pref:Developer><pref:OrgForm>ГУП</pref:OrgForm><pref:OrgName>Дирекция гаражного строительства</pref:OrgName></pref:Developer><pref:Land><pref:Contour><ns1:description xmlns:ns1="http://www.opengis.net/gml">RU77-189000-001466</ns1:description><pref:OgrFID>6207166</pref:OgrFID><pref:GEOMETRY xmlns:NS2="http://www.w3.org/1999/xlink" NS2:type="simple"><ns1:Polygon xmlns:ns1="http://www.opengis.net/gml" srsName="EPSG:4326"><ns1:outerBoundaryIs NS2:type="simple"><ns1:LinearRing><ns1:coordinates cs="," decimal="." ts=" ">37.5476458621527,55.9101876127363 37.5476950414969,55.9099979947161 37.5477281733461,55.9097618587584 37.547733481044,55.9095250149743 37.5477211312732,55.9093632631883 37.5476958303432,55.9092020552665 37.5475843330111,55.9086375219182 37.548777809898,55.9087644157639 37.5485973596458,55.9093399303631 37.5483415672241,55.9101561777963 37.5476458621527,55.9101876127363 </ns1:coordinates></ns1:LinearRing></ns1:outerBoundaryIs></ns1:Polygon></pref:GEOMETRY></pref:Contour></pref:Land><pref:GPZU><pref:DocumentNumber>RU77-189000-001466</pref:DocumentNumber><pref:DocumentDate>2010-03-26</pref:DocumentDate><pref:DocumentStatus>Действует</pref:DocumentStatus></pref:GPZU><pref:PermissionToConstruction><pref:DocumentNumber>RU77189000-007737</pref:DocumentNumber><pref:DocumentDate>2013-02-12</pref:DocumentDate><pref:ExpireDate>2015-06-30</pref:ExpireDate><pref:DocumentStatus>Действует</pref:DocumentStatus><pref:Binary>5f17e1cbeae44583bcda4d3318f094a4</pref:Binary></pref:PermissionToConstruction><pref:PermissionToConstruction><pref:DocumentNumber>RU77189000-006871</pref:DocumentNumber><pref:DocumentDate>2012-04-25</pref:DocumentDate><pref:ExpireDate>2012-12-31</pref:ExpireDate><pref:DocumentStatus>Срок действия истек</pref:DocumentStatus><pref:Binary>270c6c33b905784d9e33f7cffd787c04</pref:Binary></pref:PermissionToConstruction><pref:PermissionToConstruction><pref:DocumentNumber>RU77149000-005177</pref:DocumentNumber><pref:DocumentDate>2010-07-13</pref:DocumentDate><pref:ExpireDate>2011-07-18</pref:ExpireDate><pref:DocumentStatus>Срок действия истек</pref:DocumentStatus><pref:Binary>85f1412c9bfc5446a61e449336d5f4cf</pref:Binary></pref:PermissionToConstruction><pref:UpdateDateTime>2015-06-01T21:06:01</pref:UpdateDateTime></pref:Object></NS1:Object></NS1:ObjectNGOut></soapenv:Body></soapenv:Envelope>