<soapenv:Envelope xmlns:soapenc="http://schemas.xmlsoap.org/soap/encoding/" xmlns:soapenv="http://schemas.xmlsoap.org/soap/envelope/" xmlns:xsd="http://www.w3.org/2001/XMLSchema" xmlns:xsi="http://www.w3.org/2001/XMLSchema-instance"><soapenv:Body><NS1:ObjectNGOut xmlns:NS1="http://issk.ugd.mos.ru/MSG_RC/ObjectNGOut/v1.0"><NS1:requestID>6a0b56d4-1ee1-11e5-a5d6-ac1050040000</NS1:requestID><NS1:delete>0</NS1:delete><NS1:Object><pref:Object xmlns:pref="http://xmlns.oracle.com/MSG_RC_ObjectNG"><pref:ObjectID>0877ED5392DD8E2BC325743A004E3CEE</pref:ObjectID><pref:ObjectName>Многофункциональный офисно-рекреационный комплекс (подземное общественно-техническое пространство между участками № 12 и № 13)</pref:ObjectName><pref:ObjectArea>ЦАО</pref:ObjectArea><pref:ObjectDistrict>Пресненский</pref:ObjectDistrict><pref:ObjectAddress>Москва, ЦАО, район Пресненский, Краснопресненская набережная, ММДЦ &quot;Москва-Сити&quot;, участок № 13</pref:ObjectAddress><pref:PointXY><pref:Contour><ns1:description xmlns:ns1="http://www.opengis.net/gml">0877ED5392DD8E2BC325743A004E3CEE</ns1:description><pref:OgrFID>169636438</pref:OgrFID><pref:GEOMETRY xmlns:NS1="http://www.w3.org/1999/xlink" NS1:type="simple"><ns1:Point xmlns:ns1="http://www.opengis.net/gml" srsName="EPSG:4326"><ns1:coordinates cs="," decimal="." ts=" ">37.5361076708589,55.7492783899622 </ns1:coordinates></ns1:Point></pref:GEOMETRY></pref:Contour></pref:PointXY><pref:ConstructionWorkType>Новое строительство</pref:ConstructionWorkType><pref:MainFunctional>Административные объекты</pref:MainFunctional><pref:SourceOfFinance>Внебюджетные источники</pref:SourceOfFinance><pref:Square/><pref:Floor>4</pref:Floor><pref:ObjectStatus>В строительстве</pref:ObjectStatus><pref:Developer><pref:OrgForm>ЗАО</pref:OrgForm><pref:OrgName>Башня Федерация</pref:OrgName></pref:Developer><pref:Land><pref:Contour><ns1:description xmlns:ns1="http://www.opengis.net/gml">77:01:0004042:5011</ns1:description><pref:OgrFID>5868171</pref:OgrFID><pref:GEOMETRY xmlns:NS2="http://www.w3.org/1999/xlink" NS2:type="simple"><ns1:Polygon xmlns:ns1="http://www.opengis.net/gml" srsName="EPSG:4326"><ns1:outerBoundaryIs NS2:type="simple"><ns1:LinearRing><ns1:coordinates cs="," decimal="." ts=" ">37.533740656291,55.7490454458201 37.5354221441058,55.7496040892705 37.5374230751456,55.7502686877734 37.5374434665093,55.7502764957125 37.5375011693602,55.7506687997091 37.5379522302093,55.7502360131213 37.5360398599452,55.7496008575692 37.5366621208186,55.7490049177499 37.5365251284513,55.7489594208486 37.5363193184138,55.7488872682558 37.5362715264032,55.7488668039188 37.53622548497,55.7488450816111 37.5361811941979,55.7488221911518 37.5361388134137,55.7487982223136 37.5360983425354,55.7487730852813 37.5360601002136,55.7487469595985 37.5360239272857,55.7487199351307 37.5359901421541,55.7486919219701 37.5359585857371,55.7486630997993 37.5359294172744,55.7486334685737 37.5359026368443,55.7486031181123 37.5358785630096,55.7485721381417 37.53585687728,55.7485405287556 37.5358378982987,55.7485084694974 37.5358214667359,55.7484758705974 37.535807741991,55.7484429116449 37.5357967240576,55.7484095926407 37.5357884130105,55.7483760034029 37.5357829682475,55.7483423235204 37.5357800711966,55.7483084632682 37.535780040497,55.7482746021891 37.5357828761413,55.748240740283 37.5357884190437,55.74820705723 37.5357966691159,55.7481734632127 37.5358076265139,55.7481401378649 37.5358212913125,55.7481071710029 37.5358376635053,55.748074562626 37.5358567431675,55.7480424025502 37.5358783711344,55.7480107806375 37.5359025474824,55.7479797867038 37.5359292722067,55.7479494207476 37.5359583862262,55.7479198624478 37.5358871558719,55.7478648251224 37.5358050643305,55.7479488279404 37.5357414488866,55.7480378551444 37.5356972637874,55.748130469413 37.5352039477361,55.7481442625933 37.5352095772529,55.7482071330436 37.5338447533618,55.7482452360119 37.5337159474796,55.7484556229684 37.5352275963977,55.7484134380578 37.5352354793574,55.748503163209 37.5357127168566,55.7484898236194 37.5357792218842,55.7486011777912 37.5358739072213,55.7487057874885 37.5359948600735,55.7488014077715 37.5361393715931,55.7488860633741 37.53555974601,55.749441301156 37.5336345510732,55.7488018005548 37.533740656291,55.7490454458201 </ns1:coordinates></ns1:LinearRing></ns1:outerBoundaryIs></ns1:Polygon></pref:GEOMETRY></pref:Contour></pref:Land><pref:GPZU><pref:DocumentNumber>RU77-181000-011465</pref:DocumentNumber><pref:DocumentDate>2014-03-25</pref:DocumentDate><pref:DocumentStatus>Действует</pref:DocumentStatus></pref:GPZU><pref:PermissionToConstruction><pref:DocumentNumber>RU77181000-007689</pref:DocumentNumber><pref:DocumentDate>2013-02-04</pref:DocumentDate><pref:ExpireDate>2014-02-01</pref:ExpireDate><pref:DocumentStatus>Срок действия истек</pref:DocumentStatus><pref:Binary>9a74851fd95f4b2b865649343edd4a3b</pref:Binary></pref:PermissionToConstruction><pref:PermissionToConstruction><pref:DocumentNumber>RU77181000-007335</pref:DocumentNumber><pref:DocumentDate>2012-10-09</pref:DocumentDate><pref:ExpireDate>2013-01-09</pref:ExpireDate><pref:DocumentStatus>Срок действия истек</pref:DocumentStatus><pref:Binary>c9c14598c8b60040b212f613c467bf66</pref:Binary></pref:PermissionToConstruction><pref:PermissionToConstruction><pref:DocumentNumber>RU77181000-004702</pref:DocumentNumber><pref:DocumentDate>2010-03-22</pref:DocumentDate><pref:ExpireDate>2012-10-15</pref:ExpireDate><pref:DocumentStatus>Срок действия истек</pref:DocumentStatus><pref:Binary>788d8703ec1d6546832cf7acd43388d5</pref:Binary></pref:PermissionToConstruction><pref:PermissionToConstruction><pref:DocumentNumber>RU77181000-003195</pref:DocumentNumber><pref:DocumentDate>2008-12-08</pref:DocumentDate><pref:ExpireDate>2010-03-15</pref:ExpireDate><pref:DocumentStatus>Срок действия истек</pref:DocumentStatus><pref:Binary>959498dd074a8d4f9b8094125cc7d3cc</pref:Binary></pref:PermissionToConstruction><pref:UpdateDateTime>2015-06-29T10:06:29</pref:UpdateDateTime></pref:Object></NS1:Object></NS1:ObjectNGOut></soapenv:Body></soapenv:Envelope>